b10_vidbench/__init__.py
b10_vidbench/analyzer.py
b10_vidbench-0.2.0.dist-info/METADATA
b10_vidbench-0.2.0.dist-info/WHEEL
b10_vidbench-0.2.0.dist-info/RECORD
