Metadata-Version: 2.3
Name: b10-vidbench
Version: 0.2.0
Summary: Simple video quality analysis using VBench
License: MIT
Keywords: video,quality,vbench,ai
Author: Shounak Ray
Author-email: shounak.ray@baseten.co
Requires-Python: >=3.8
Classifier: License :: OSI Approved :: MIT License
Classifier: Programming Language :: Python :: 3
Classifier: Programming Language :: Python :: 3.8
Classifier: Programming Language :: Python :: 3.9
Classifier: Programming Language :: Python :: 3.10
Classifier: Programming Language :: Python :: 3.11
Classifier: Programming Language :: Python :: 3.12
Classifier: Programming Language :: Python :: 3.13
Provides-Extra: vbench
Requires-Dist: numpy
Requires-Dist: opencv-python
Requires-Dist: pillow
Requires-Dist: vbench ; extra == "vbench"
